LICENSE
MANIFEST.in
README.md
requirements.txt
setup.cfg
setup.py
intellino/__init__.py
intellino.egg-info/PKG-INFO
intellino.egg-info/SOURCES.txt
intellino.egg-info/dependency_links.txt
intellino.egg-info/not-zip-safe
intellino.egg-info/requires.txt
intellino.egg-info/top_level.txt
intellino/core/__init__.py
intellino/core/neuron_cell.py
intellino/utils/data/__init__.py
intellino/utils/data/dataloader.py
intellino/utils/data/dataset.py