Metadata-Version: 2.1
Name: intellino
Version: 0.0.1.dev13
Summary: The Intellino core logic wrapper for ML simulation with intellino
Home-page: https://github.com/Intellino/intellino
Author: SoC Platform Lab
Author-email: hwangdonghyun@seoultech.ac.kr
License: GPLv3
Download-URL: https://github.com/Intellino/intellino
Keywords: intellino
Platform: UNKNOWN
Classifier: Natural Language :: English
Classifier: Programming Language :: Python :: 3
Classifier: Programming Language :: Python :: 3.6
Classifier: Programming Language :: Python :: 3.7
Classifier: License :: OSI Approved :: GNU General Public License v3 (GPLv3)
Classifier: Operating System :: OS Independent
Classifier: Topic :: Scientific/Engineering :: Artificial Intelligence
Classifier: Development Status :: 3 - Alpha
Requires-Python: >=3.6
